[
  {
    "_type": "snscrape.modules.twitter.Tweet",
    "url": "https://twitter.com/julie_witherow/status/1488940883672186887",
    "date": "2022-02-02T18:22:24+00:00",
    "content": "STOP HARINGEY COUNCIL KILLING MORE TREES WITH THEIR NATURE-WRECKING NEW BRIDGE DESIGN! - Sign the Petition! https://t.co/z7jGLX0iLj via @UKChange",
    "renderedContent": "STOP HARINGEY COUNCIL KILLING MORE TREES WITH THEIR NATURE-WRECKING NEW BRIDGE DESIGN! - Sign the Petition! chng.it/hPngwggm via @UKChange",
    "id": 1488940883672186887,
    "user": {
      "_type": "snscrape.modules.twitter.User",
      "username": "julie_witherow",
      "id": 980832428213374976,
      "displayname": "Julie Witherow",
      "description": "#pigeoneer . Passionate about animal welfare/rights.\n\n\"I am I.\"  Sylvia Plath",
      "rawDescription": "#pigeoneer . Passionate about animal welfare/rights.\n\n\"I am I.\"  Sylvia Plath",
      "descriptionUrls": null,
      "verified": false,
      "created": "2018-04-02T15:40:48+00:00",
      "followersCount": 452,
      "friendsCount": 590,
      "statusesCount": 15687,
      "favouritesCount": 29070,
      "listedCount": 6,
      "mediaCount": 106,
      "location": "Northern Ireland",
      "protected": false,
      "linkUrl": null,
      "linkTcourl": null,
      "profileImageUrl": "https://pbs.twimg.com/profile_images/1375396424590966785/n2vwJ-ci_normal.jpg",
      "profileBannerUrl": "https://pbs.twimg.com/profile_banners/980832428213374976/1633367074",
      "label": null,
      "url": "https://twitter.com/julie_witherow"
    },
    "replyCount": 0,
    "retweetCount": 0,
    "likeCount": 0,
    "quoteCount": 0,
    "conversationId": 1488940883672186887,
    "lang": "en",
    "source": "<a href=\"https://mobile.twitter.com\" rel=\"nofollow\">Twitter Web App</a>",
    "sourceUrl": "https://mobile.twitter.com",
    "sourceLabel": "Twitter Web App",
    "outlinks": ["https://chng.it/hPngwggm"],
    "tcooutlinks": ["https://t.co/z7jGLX0iLj"],
    "media": null,
    "retweetedTweet": null,
    "quotedTweet": null,
    "inReplyToTweetId": null,
    "inReplyToUser": null,
    "mentionedUsers": [
      {
        "_type": "snscrape.modules.twitter.User",
        "username": "UKChange",
        "id": 397998902,
        "displayname": "Change.org UK",
        "description": null,
        "rawDescription": null,
        "descriptionUrls": null,
        "verified": null,
        "created": null,
        "followersCount": null,
        "friendsCount": null,
        "statusesCount": null,
        "favouritesCount": null,
        "listedCount": null,
        "mediaCount": null,
        "location": null,
        "protected": null,
        "linkUrl": null,
        "linkTcourl": null,
        "profileImageUrl": null,
        "profileBannerUrl": null,
        "label": null,
        "url": "https://twitter.com/UKChange"
      }
    ],
    "coordinates": null,
    "place": null,
    "hashtags": null,
    "cashtags": null
  },
  {
    "_type": "snscrape.modules.twitter.Tweet",
    "url": "https://twitter.com/TCVHaringey/status/1492130156588290051",
    "date": "2022-02-11T13:35:26+00:00",
    "content": "Fantastic day with this lovely bunch at Lordship Rec spinny litter picking, #coppicing, building deadhedges and crown lifting. #trees #volunteer #Haringey https://t.co/q1wBJsBM9C",
    "renderedContent": "Fantastic day with this lovely bunch at Lordship Rec spinny litter picking, #coppicing, building deadhedges and crown lifting. #trees #volunteer #Haringey https://t.co/q1wBJsBM9C",
    "id": 1492130156588290051,
    "user": {
      "_type": "snscrape.modules.twitter.User",
      "username": "TCVHaringey",
      "id": 1647375942,
      "displayname": "TCV Haringey",
      "description": "Conservation, Volunteering, Education, Wildlife Surveying & more!\n\nCreating Healthier and Happier communities for everyone across Haringey.",
      "rawDescription": "Conservation, Volunteering, Education, Wildlife Surveying & more!\n\nCreating Healthier and Happier communities for everyone across Haringey.",
      "descriptionUrls": null,
      "verified": false,
      "created": "2013-08-05T09:41:36+00:00",
      "followersCount": 715,
      "friendsCount": 690,
      "statusesCount": 1848,
      "favouritesCount": 1703,
      "listedCount": 10,
      "mediaCount": 939,
      "location": "Haringey, London",
      "protected": false,
      "linkUrl": "https://www.tcv.org.uk/london/haringey",
      "linkTcourl": "https://t.co/MhrnDTASaP",
      "profileImageUrl": "https://pbs.twimg.com/profile_images/1234448839102345218/I0uAyBeL_normal.jpg",
      "profileBannerUrl": "https://pbs.twimg.com/profile_banners/1647375942/1623419382",
      "label": null,
      "url": "https://twitter.com/TCVHaringey"
    },
    "replyCount": 0,
    "retweetCount": 0,
    "likeCount": 4,
    "quoteCount": 0,
    "conversationId": 1492130156588290051,
    "lang": "en",
    "source": "<a href=\"http://twitter.com/download/android\" rel=\"nofollow\">Twitter for Android</a>",
    "sourceUrl": "http://twitter.com/download/android",
    "sourceLabel": "Twitter for Android",
    "outlinks": null,
    "tcooutlinks": null,
    "media": [
      {
        "_type": "snscrape.modules.twitter.Photo",
        "previewUrl": "https://pbs.twimg.com/media/FLUcdQLXMAk1A3x?format=jpg&name=small",
        "fullUrl": "https://pbs.twimg.com/media/FLUcdQLXMAk1A3x?format=jpg&name=large"
      }
    ],
    "retweetedTweet": null,
    "quotedTweet": null,
    "inReplyToTweetId": null,
    "inReplyToUser": null,
    "mentionedUsers": null,
    "coordinates": null,
    "place": null,
    "hashtags": ["coppicing", "trees", "volunteer", "Haringey"],
    "cashtags": null
  },
  {
    "_type": "snscrape.modules.twitter.Tweet",
    "url": "https://twitter.com/MartinBallN17/status/1490337208208875527",
    "date": "2022-02-06T14:50:54+00:00",
    "content": "We plant #trees say Haringey. Where are they ask the public. Are these eight on Marigold Road N17 some of them? Location is off Watermead Way across from Lea Valley Park. Do we need more here or on our urban streets? Discuss. Hope Trees for Streets not collecting 250 a tree here. https://t.co/5F0pncMfZt",
    "renderedContent": "We plant #trees say Haringey. Where are they ask the public. Are these eight on Marigold Road N17 some of them? Location is off Watermead Way across from Lea Valley Park. Do we need more here or on our urban streets? Discuss. Hope Trees for Streets not collecting 250 a tree here. https://t.co/5F0pncMfZt",
    "id": 1490337208208875527,
    "user": {
      "_type": "snscrape.modules.twitter.User",
      "username": "MartinBallN17",
      "id": 1263091717,
      "displayname": "N17 Creative Action",
      "description": "Tottenham Hale resident working with others to improve N17 area through creative action. Photos @ flickr.com/photos/1314782\u2026 & videos @",
      "rawDescription": "Tottenham Hale resident working with others to improve N17 area through creative action. Photos @ https://t.co/PiQQ4gcVH7 & videos @",
      "descriptionUrls": [
        {
          "text": "flickr.com/photos/1314782\u2026",
          "url": "https://www.flickr.com/photos/131478208@N05/albums",
          "tcourl": "https://t.co/PiQQ4gcVH7",
          "indices": [98, 121]
        }
      ],
      "verified": false,
      "created": "2013-03-12T23:10:17+00:00",
      "followersCount": 3291,
      "friendsCount": 482,
      "statusesCount": 44705,
      "favouritesCount": 33613,
      "listedCount": 0,
      "mediaCount": 15288,
      "location": "",
      "protected": false,
      "linkUrl": "https://m.youtube.com/playlist?list=UU4mhwzjxXbQWxiagqwNgVNg",
      "linkTcourl": "https://t.co/g9EnB9tPuF",
      "profileImageUrl": "https://pbs.twimg.com/profile_images/1294331972370800640/j83M7TDK_normal.jpg",
      "profileBannerUrl": "https://pbs.twimg.com/profile_banners/1263091717/1622715256",
      "label": null,
      "url": "https://twitter.com/MartinBallN17"
    },
    "replyCount": 1,
    "retweetCount": 0,
    "likeCount": 2,
    "quoteCount": 0,
    "conversationId": 1490337208208875527,
    "lang": "en",
    "source": "<a href=\"https://mobile.twitter.com\" rel=\"nofollow\">Twitter Web App</a>",
    "sourceUrl": "https://mobile.twitter.com",
    "sourceLabel": "Twitter Web App",
    "outlinks": null,
    "tcooutlinks": null,
    "media": [
      {
        "_type": "snscrape.modules.twitter.Photo",
        "previewUrl": "https://pbs.twimg.com/media/FK69KFfWYAERAHx?format=jpg&name=small",
        "fullUrl": "https://pbs.twimg.com/media/FK69KFfWYAERAHx?format=jpg&name=large"
      }
    ],
    "retweetedTweet": null,
    "quotedTweet": null,
    "inReplyToTweetId": null,
    "inReplyToUser": null,
    "mentionedUsers": null,
    "coordinates": null,
    "place": null,
    "hashtags": ["trees"],
    "cashtags": null
  }
]
